infix_postfix/__init__.py
infix_postfix/infix_postfix.py
infix_postfix-1.2.0.dist-info/LICENSE
infix_postfix-1.2.0.dist-info/METADATA
infix_postfix-1.2.0.dist-info/WHEEL
infix_postfix-1.2.0.dist-info/entry_points.txt
infix_postfix-1.2.0.dist-info/top_level.txt
infix_postfix-1.2.0.dist-info/RECORD
