Metadata-Version: 2.1
Name: infix-postfix
Version: 1.2.0
Summary: Converts Infix to Postfix and vice versa...
Home-page: https://github.com/SoumadeepChoudhury/infixpostfix
Author: Ahens | An Initiative to Initial (Soumadeep Choudhury)
Author-email: ahensinitiative@gmail.com
License: MIT
Keywords: python,arithmetic,tools,arith-tools,arithmetic operations,Math,python3,pip,pip3,fibonacci,armstrong,boiled-egg,terrace,unique,amicable,infix,postfix,infix2postfix,infixtopostfix,infix-postfix,infix_postfix
Classifier: Development Status :: 5 - Production/Stable
Classifier: Intended Audience :: Developers
Classifier: License :: OSI Approved :: MIT License
Classifier: Programming Language :: Python :: 3
Classifier: Programming Language :: Python :: 3.7
Classifier: Operating System :: Unix
Classifier: Operating System :: MacOS :: MacOS X
Classifier: Operating System :: Microsoft :: Windows
License-File: LICENSE
